django_redis_ratelimit-0.1.1.dist-info/DESCRIPTION.rst
django_redis_ratelimit-0.1.1.dist-info/METADATA
django_redis_ratelimit-0.1.1.dist-info/RECORD
django_redis_ratelimit-0.1.1.dist-info/WHEEL
django_redis_ratelimit-0.1.1.dist-info/metadata.json
django_redis_ratelimit-0.1.1.dist-info/top_level.txt
redis_ratelimit/__init__.py
redis_ratelimit/decorators.py
redis_ratelimit/exceptions.py
redis_ratelimit/middleware.py
redis_ratelimit/utils.py
