Metadata-Version: 2.0
Name: django-redis-ratelimit
Version: 0.1.1
Summary: A fixed window rate limiting based on Redis
Home-page: https://github.com/r00m/django-redis-ratelimit
Author: Roman Tomjak
Author-email: r.tomjaks@gmail.com
License: MIT
Keywords: django redis rate-limit ratelimit
Platform: UNKNOWN
Classifier: Development Status :: 3 - Alpha
Classifier: Intended Audience :: Developers
Classifier: Topic :: Software Development :: Libraries :: Python Modules
Classifier: License :: OSI Approved :: MIT License
Classifier: Programming Language :: Python :: 3.6
Requires-Dist: Django (>=1.11)
Requires-Dist: redis
